<?xml version="1.0" encoding="UTF-8"?>
<!DOCTYPE generatorConfiguration
        PUBLIC "-//mybatis.org//DTD MyBatis Generator Configuration 1.0//EN"
        "http://mybatis.org/dtd/mybatis-generator-config_1_0.dtd">

<generatorConfiguration>
    <context id="Mysql" targetRuntime="MyBatis3DynamicSql" defaultModelType="flat">

        <property name="autoDelimitKeywords" value="true"/>
        <property name="javaFileEncoding" value="UTF-8"/>
        <property name="beginningDelimiter" value="`"/>
        <property name="endingDelimiter" value="`"/>

        <!-- 为模型生成序列化方法-->
        <plugin type="org.mybatis.generator.plugins.SerializablePlugin"/>
        <!--覆盖生成XML文件 默认为覆盖-->
<!--        <plugin type="org.mybatis.generator.plugins.UnmergeableXmlMappersPlugin"/>-->
        <!-- 生成的实体类添加toString()方法 -->
        <plugin type="org.mybatis.generator.plugins.ToStringPlugin"/>

        <!-- 不生成注释 -->
        <commentGenerator>
            <property name="suppressAllComments" value="true"/>
        </commentGenerator>

        <!-- 数据库配置-->
        <jdbcConnection driverClass="com.mysql.cj.jdbc.Driver"
                        connectionURL="jdbc:mysql://192.168.114.114:9010/test?characterEncoding=UTF8&amp;autoReconnect=true&amp;allowPublicKeyRetrieval=true&amp;serverTimezone=Asia/Shanghai"
                        userId="root"
                        password="root">
        </jdbcConnection>

        <!-- domain类的位置 -->
        <javaModelGenerator targetProject="server/src/main/java"
                            targetPackage="com.twj.spirngbasics.server.entity"/>

        <!-- mapper xml的位置 -->
        <sqlMapGenerator targetProject="server/src/main/resources"
                         targetPackage="mapper"/>

        <!-- mapper类的位置 -->
        <javaClientGenerator targetProject="server/src/main/java"
                             targetPackage="com.twj.spirngbasics.server.mapper"
                             type="XMLMAPPER"/>

<!--                <table tableName="test" domainObjectName="Test"/>-->
<!--                <table tableName="user_resource" domainObjectName="UserResource"/>-->
<!--                <table tableName="user_role" domainObjectName="UserRole"/>-->
<!--                <table tableName="user_role_resource" domainObjectName="UserRoleResource"/>-->
<!--                <table tableName="user_role_user" domainObjectName="UserRoleUser"/>-->
                <table tableName="sys_dict" domainObjectName="SysDict"/>


    </context>
</generatorConfiguration>
